{"id":["108277846301435391"],"username":["imick"],"acct":["imick@m.cmx.im"],"display_name":["IronMick-tt8"],"locked":[false],"bot":[false],"discoverable":[true],"indexable":[false],"group":[false],"created_at":["2022-03-15T00:00:00.000Z"],"note":["<p>Comic，Manga 两手抓，两手都要硬。<\/p><p>A typophile.<\/p><p>A collector of vintage Penguin books.<\/p><p>A lumber hoarder.<\/p><p>一个没有办法扔掉边角料的人。<\/p><p>生命不息，减肥不止。<\/p><p>纹丝不动，严丝合缝。<\/p><p>May the grain be with you!<\/p><p>Liv i Trä.<\/p>"],"url":["https://m.cmx.im/@imick"],"uri":["https://m.cmx.im/users/imick"],"avatar":["https://files.mastodon.social/cache/accounts/avatars/108/277/846/301/435/391/original/1baac1de9ce40372.jpeg"],"avatar_static":["https://files.mastodon.social/cache/accounts/avatars/108/277/846/301/435/391/original/1baac1de9ce40372.jpeg"],"header":["https://files.mastodon.social/cache/accounts/headers/108/277/846/301/435/391/original/b995e7be95bd059d.jpeg"],"header_static":["https://files.mastodon.social/cache/accounts/headers/108/277/846/301/435/391/original/b995e7be95bd059d.jpeg"],"followers_count":[289],"following_count":[82],"statuses_count":[2162],"last_status_at":["2024-10-25"],"hide_collections":[false],"emojis":[],"fields":[]}
