{"id":["108230524126427693"],"username":["kenhung"],"acct":["kenhung"],"display_name":["Kenneth Hung"],"locked":[false],"bot":[false],"discoverable":[false],"group":[false],"created_at":["2022-05-02"],"note":["<p>Statistician at Meta; PhD ‘19 at UC Berkeley; BSc ‘14 at Caltech; 🇨🇦🇭🇰🇺🇸<\/p>"],"url":["https://mastodon.social/@kenhung"],"avatar":["https://files.mastodon.social/accounts/avatars/108/230/524/126/427/693/original/bac726c8471f1e70.jpg"],"avatar_static":["https://files.mastodon.social/accounts/avatars/108/230/524/126/427/693/original/bac726c8471f1e70.jpg"],"header":["https://files.mastodon.social/accounts/headers/108/230/524/126/427/693/original/0cde9a13729615e4.jpeg"],"header_static":["https://files.mastodon.social/accounts/headers/108/230/524/126/427/693/original/0cde9a13729615e4.jpeg"],"followers_count":[0],"following_count":[17],"statuses_count":[12],"fields":[{"name":"Website","value":"<a href=\"https://kenhung.me\" target=\"_blank\" rel=\"nofollow noopener noreferrer me\" translate=\"no\"><span class=\"invisible\">https://<\/span><span class=\"\">kenhung.me<\/span><span class=\"invisible\"><\/span><\/a>"},{"name":"Email","value":"me@kenhung.me"}],"emojis":[]}
