{"id":["109273929491312537"],"username":["thisisfilber7"],"acct":["thisisfilber7@mas.to"],"display_name":["FILBERT :debian: ☸️"],"locked":[true],"bot":[false],"group":[false],"created_at":["2022-11-02"],"note":["<p>See my bio <span class=\"h-card\"><a href=\"https://i.calckey.cloud/@thisisfilbert\" class=\"u-url mention\" rel=\"nofollow noopener noreferrer\" target=\"_blank\">@<span>thisisfilbert<\/span><\/a><\/span><\/p>"],"url":["https://mas.to/@thisisfilber7"],"avatar":["https://files.mastodon.social/cache/accounts/avatars/109/273/929/491/312/537/original/51c7ab82b304f729.png"],"avatar_static":["https://files.mastodon.social/cache/accounts/avatars/109/273/929/491/312/537/original/51c7ab82b304f729.png"],"header":["https://files.mastodon.social/cache/accounts/headers/109/273/929/491/312/537/original/a0e5fc7eaa82da85.png"],"header_static":["https://files.mastodon.social/cache/accounts/headers/109/273/929/491/312/537/original/a0e5fc7eaa82da85.png"],"followers_count":[34],"following_count":[178],"statuses_count":[8],"fields":[{"name":"Page","value":"<a href=\"https://thisisfilber7.codeberg.page\" target=\"_blank\" rel=\"nofollow noopener noreferrer\" translate=\"no\"><span class=\"invisible\">https://<\/span><span class=\"\">thisisfilber7.codeberg.page<\/span><span class=\"invisible\"><\/span><\/a>","verified_at":"2023-07-02T08:53:53.212+00:00"},{"name":"Distro","value":"<span class=\"h-card\"><a href=\"https://framapiaf.org/@debian\" class=\"u-url mention\" rel=\"nofollow noopener noreferrer\" target=\"_blank\">@<span>debian@framapiaf.org<\/span><\/a><\/span>"},{"name":"Will migrate to","value":"<span class=\"h-card\"><a href=\"https://kitsunes.club/@thisisfilbert\" class=\"u-url mention\" rel=\"nofollow noopener noreferrer\" target=\"_blank\">@<span>thisisfilbert@kitsunes.club<\/span><\/a><\/span>"},{"name":"Location","value":"Sumatra Island"}],"emojis":[{"shortcode":"debian","url":"https://files.mastodon.social/cache/custom_emojis/images/000/594/950/original/e89499a936f8da46.png","static_url":"https://files.mastodon.social/cache/custom_emojis/images/000/594/950/static/e89499a936f8da46.png","visible_in_picker":true}],"discoverable":[false]}
