{"id":["109257354228680757"],"username":["ruipontecosta"],"acct":["ruipontecosta"],"display_name":["Rui Ponte Costa"],"locked":[false],"bot":[false],"discoverable":[false],"indexable":[false],"group":[false],"created_at":["2022-10-30T00:00:00.000Z"],"note":["<p>Bringing neural and machine learning closer together  |  neuralml.github.io<\/p>"],"url":["https://mastodon.social/@ruipontecosta"],"uri":["https://mastodon.social/users/ruipontecosta"],"avatar":["https://files.mastodon.social/accounts/avatars/109/257/354/228/680/757/original/13a10fe706c20b31.png"],"avatar_static":["https://files.mastodon.social/accounts/avatars/109/257/354/228/680/757/original/13a10fe706c20b31.png"],"header":["https://files.mastodon.social/accounts/headers/109/257/354/228/680/757/original/e182badd63342e3d.jpg"],"header_static":["https://files.mastodon.social/accounts/headers/109/257/354/228/680/757/original/e182badd63342e3d.jpg"],"followers_count":[429],"following_count":[79],"statuses_count":[144],"last_status_at":["2024-09-09"],"hide_collections":[false],"noindex":[false],"emojis":[],"roles":[],"fields":[]}
