{"id":["109286418625239055"],"username":["alex"],"acct":["alex@climatejustice.social"],"display_name":["AlexOz"],"locked":[false],"bot":[false],"discoverable":[true],"indexable":[true],"group":[false],"created_at":["2022-06-05T00:00:00.000Z"],"note":["<p>Extinction rebel, concerned earthling, IT guy.<\/p>"],"url":["https://climatejustice.social/@alex"],"uri":["https://climatejustice.social/users/alex"],"avatar":["https://files.mastodon.social/cache/accounts/avatars/109/286/418/625/239/055/original/384724b2a8ed864f.jpg"],"avatar_static":["https://files.mastodon.social/cache/accounts/avatars/109/286/418/625/239/055/original/384724b2a8ed864f.jpg"],"header":["https://files.mastodon.social/cache/accounts/headers/109/286/418/625/239/055/original/14e9aabe66a9c4e8.jpg"],"header_static":["https://files.mastodon.social/cache/accounts/headers/109/286/418/625/239/055/original/14e9aabe66a9c4e8.jpg"],"followers_count":[44],"following_count":[476],"statuses_count":[376],"last_status_at":["2024-10-28"],"hide_collections":[false],"emojis":[],"fields":[]}
