{"id":["109362177309148257"],"username":["pgd543"],"acct":["pgd543"],"display_name":["PGD543"],"locked":[false],"bot":[false],"discoverable":[true],"indexable":[false],"group":[false],"created_at":["2022-11-18T00:00:00.000Z"],"note":["<p>Just your usual living flesh sack which somehow gained emotional capability.<\/p>"],"url":["https://mastodon.social/@pgd543"],"uri":["https://mastodon.social/users/pgd543"],"avatar":["https://files.mastodon.social/accounts/avatars/109/362/177/309/148/257/original/afef4f4a3bcba1a6.jpeg"],"avatar_static":["https://files.mastodon.social/accounts/avatars/109/362/177/309/148/257/original/afef4f4a3bcba1a6.jpeg"],"header":["https://files.mastodon.social/accounts/headers/109/362/177/309/148/257/original/ee7ee1a30f732a62.png"],"header_static":["https://files.mastodon.social/accounts/headers/109/362/177/309/148/257/original/ee7ee1a30f732a62.png"],"followers_count":[0],"following_count":[2],"statuses_count":[0],"last_status_at":{},"hide_collections":[false],"noindex":[false],"emojis":[],"roles":[],"fields":[]}
