{"id":["109367381658292718"],"username":["panicopticon"],"acct":["panicopticon@infosec.exchange"],"display_name":["panicopticon"],"locked":[false],"bot":[false],"group":[false],"created_at":["2022-11-05"],"note":[""],"url":["https://infosec.exchange/@panicopticon"],"avatar":["https://files.mastodon.social/cache/accounts/avatars/109/367/381/658/292/718/original/bc8459ebedd8cfc0.jpeg"],"avatar_static":["https://files.mastodon.social/cache/accounts/avatars/109/367/381/658/292/718/original/bc8459ebedd8cfc0.jpeg"],"header":["https://mastodon.social/headers/original/missing.png"],"header_static":["https://mastodon.social/headers/original/missing.png"],"followers_count":[23],"following_count":[192],"statuses_count":[231],"fields":[],"emojis":[],"discoverable":[false]}
