{"id":["109346797832054610"],"username":["tounesbelalb"],"acct":["tounesbelalb@techhub.social"],"display_name":["SOFIEN TABOUBI"],"locked":[true],"bot":[false],"discoverable":[true],"indexable":[false],"group":[false],"created_at":["2022-11-13T00:00:00.000Z"],"note":["<p>رضيت بالله ربّا و بالإسلام دينا و بمحمّد ﷺ نبيّا متابع جيّد لكُلّ ما هو جديد في عالم التّكنلوجيا<\/p>"],"url":["https://techhub.social/@tounesbelalb"],"uri":["https://techhub.social/users/tounesbelalb"],"avatar":["https://files.mastodon.social/cache/accounts/avatars/109/346/797/832/054/610/original/c411d226ab2283c2.png"],"avatar_static":["https://files.mastodon.social/cache/accounts/avatars/109/346/797/832/054/610/original/c411d226ab2283c2.png"],"header":["https://files.mastodon.social/cache/accounts/headers/109/346/797/832/054/610/original/10c84c477de63afc.png"],"header_static":["https://files.mastodon.social/cache/accounts/headers/109/346/797/832/054/610/original/10c84c477de63afc.png"],"followers_count":[0],"following_count":[8],"statuses_count":[1],"last_status_at":{},"hide_collections":[true],"emojis":[],"fields":[{"name":["رضيت بالله ربّا و بالإسلام دينا و بمحمّد ﷺ نبيّا"],"value":[""],"verified_at":{}},{"name":["متابع جيّد لكُلّ ما هو جديد في عالم التّكنلوجيا"],"value":[""],"verified_at":{}}]}
