{"id":["109350144084984171"],"username":["egil"],"acct":["egil"],"display_name":["Egil Hansen"],"locked":[false],"bot":[false],"discoverable":[true],"indexable":[true],"group":[false],"created_at":["2022-11-15T00:00:00.000Z"],"note":["<p>Distinguished Developer at Delegate A/S, Microsoft <a href=\"https://mastodon.social/tags/MVP\" class=\"mention hashtag\" rel=\"tag\">#<span>MVP<\/span><\/a> and creator of <a href=\"https://mastodon.social/tags/bUnit\" class=\"mention hashtag\" rel=\"tag\">#<span>bUnit<\/span><\/a> (<a href=\"https://bunit.dev\" target=\"_blank\" rel=\"nofollow noopener noreferrer\" translate=\"no\"><span class=\"invisible\">https://<\/span><span class=\"\">bunit.dev<\/span><span class=\"invisible\"><\/span><\/a>). 🇩🇰 living in 🇮🇸.<\/p>"],"url":["https://mastodon.social/@egil"],"uri":["https://mastodon.social/users/egil"],"avatar":["https://files.mastodon.social/accounts/avatars/109/350/144/084/984/171/original/1e3855fc4edc9235.jpg"],"avatar_static":["https://files.mastodon.social/accounts/avatars/109/350/144/084/984/171/original/1e3855fc4edc9235.jpg"],"header":["https://files.mastodon.social/accounts/headers/109/350/144/084/984/171/original/15b849abd439bba3.jpg"],"header_static":["https://files.mastodon.social/accounts/headers/109/350/144/084/984/171/original/15b849abd439bba3.jpg"],"followers_count":[209],"following_count":[221],"statuses_count":[263],"last_status_at":["2024-08-25"],"hide_collections":[false],"noindex":[false],"emojis":[],"roles":[],"fields":[{"name":["LinkedIn"],"value":["<a href=\"https://www.linkedin.com/in/egilhansen/\" target=\"_blank\" rel=\"nofollow noopener noreferrer me\" translate=\"no\"><span class=\"invisible\">https://www.<\/span><span class=\"\">linkedin.com/in/egilhansen/<\/span><span class=\"invisible\"><\/span><\/a>"],"verified_at":{}},{"name":["Blog"],"value":["<a href=\"https://egilhansen.com\" target=\"_blank\" rel=\"nofollow noopener noreferrer me\" translate=\"no\"><span class=\"invisible\">https://<\/span><span class=\"\">egilhansen.com<\/span><span class=\"invisible\"><\/span><\/a>"],"verified_at":["2023-12-25T10:37:00.183+00:00"]},{"name":["GitHub"],"value":["<a href=\"https://github.com/egil\" target=\"_blank\" rel=\"nofollow noopener noreferrer me\" translate=\"no\"><span class=\"invisible\">https://<\/span><span class=\"\">github.com/egil<\/span><span class=\"invisible\"><\/span><\/a>"],"verified_at":["2023-12-25T10:37:23.613+00:00"]},{"name":["Twitter"],"value":["<a href=\"https://twitter.com/egilhansen\" target=\"_blank\" rel=\"nofollow noopener noreferrer me\" translate=\"no\"><span class=\"invisible\">https://<\/span><span class=\"\">twitter.com/egilhansen<\/span><span class=\"invisible\"><\/span><\/a>"],"verified_at":{}}]}
