{"id":["109507398788950366"],"username":["reis_marcelo"],"acct":["reis_marcelo"],"display_name":["Marcelo Reis"],"locked":[false],"bot":[false],"discoverable":[false],"indexable":[false],"group":[false],"created_at":["2022-12-13T00:00:00.000Z"],"note":[""],"url":["https://mastodon.social/@reis_marcelo"],"uri":["https://mastodon.social/users/reis_marcelo"],"avatar":["https://files.mastodon.social/accounts/avatars/109/507/398/788/950/366/original/02b318727bce51d2.jpg"],"avatar_static":["https://files.mastodon.social/accounts/avatars/109/507/398/788/950/366/original/02b318727bce51d2.jpg"],"header":["https://files.mastodon.social/accounts/headers/109/507/398/788/950/366/original/928729c89c6789bf.jpg"],"header_static":["https://files.mastodon.social/accounts/headers/109/507/398/788/950/366/original/928729c89c6789bf.jpg"],"followers_count":[0],"following_count":[12],"statuses_count":[0],"last_status_at":{},"hide_collections":[false],"noindex":[false],"emojis":[],"roles":[],"fields":[]}
