{"id":["109554336823520032"],"username":["salarua"],"acct":["salarua@outerheaven.club"],"display_name":["salarua"],"locked":[true],"bot":[false],"group":[false],"created_at":["2022-12-21"],"note":["just a random guy on the internet. interested in art, philosophy, current events, tech, politics (i promise to cw it), games, and really whatever else catches my attention"],"url":["https://outerheaven.club/users/salarua"],"avatar":["https://files.mastodon.social/cache/accounts/avatars/109/554/336/823/520/032/original/d0596d0896099750.png"],"avatar_static":["https://files.mastodon.social/cache/accounts/avatars/109/554/336/823/520/032/original/d0596d0896099750.png"],"header":["https://mastodon.social/headers/original/missing.png"],"header_static":["https://mastodon.social/headers/original/missing.png"],"followers_count":[0],"following_count":[84],"statuses_count":[3],"fields":[],"emojis":[],"discoverable":[false]}
