{"id":["111103365859009261"],"username":["humbertolopes"],"acct":["humbertolopes"],"display_name":["Humberto Lopes"],"locked":[false],"bot":[false],"discoverable":{},"indexable":[false],"group":[false],"created_at":["2023-09-21T00:00:00.000Z"],"note":["<p>ultimatecamp.com.br<\/p>"],"url":["https://mastodon.social/@humbertolopes"],"uri":["https://mastodon.social/users/humbertolopes"],"avatar":["https://files.mastodon.social/accounts/avatars/111/103/365/859/009/261/original/7d7e2ded1649b079.png"],"avatar_static":["https://files.mastodon.social/accounts/avatars/111/103/365/859/009/261/original/7d7e2ded1649b079.png"],"header":["https://mastodon.social/headers/original/missing.png"],"header_static":["https://mastodon.social/headers/original/missing.png"],"followers_count":[0],"following_count":[1],"statuses_count":[0],"last_status_at":{},"hide_collections":{},"noindex":[false],"emojis":[],"roles":[],"fields":[]}
