{"id":["111176747005400061"],"username":["69vnwin"],"acct":["69vnwin@masto.ai"],"display_name":["69vn"],"locked":[false],"bot":[false],"discoverable":[false],"indexable":[false],"group":[false],"created_at":["2023-08-04T00:00:00.000Z"],"note":["<p>Nếu anh em đang tìm nhà cái hiện đại, tiên tiến và đáp ứng đầy đủ các tiêu chí game. Thì 69VN là sự lựa chọn tuyệt vời nhất để có những trải nghiệm thú vị.<br>Website:       <a href=\"https://69vn.win/\" rel=\"nofollow noopener noreferrer\" translate=\"no\" target=\"_blank\"><span class=\"invisible\">https://<\/span><span class=\"\">69vn.win/<\/span><span class=\"invisible\"><\/span><\/a><br>địa chỉ:  24/5B Tổ 124 ấp Đông, Tân Chánh Hiệp, Hóc Môn, Thành phố Hồ Chí Minh, Việt Nam<br>Hastag       <a href=\"https://masto.ai/tags/69vn\" class=\"mention hashtag\" rel=\"nofollow noopener noreferrer\" target=\"_blank\">#<span>69vn<\/span><\/a> <a href=\"https://masto.ai/tags/69vnwin\" class=\"mention hashtag\" rel=\"nofollow noopener noreferrer\" target=\"_blank\">#<span>69vnwin<\/span><\/a> <a href=\"https://masto.ai/tags/vn69\" class=\"mention hashtag\" rel=\"nofollow noopener noreferrer\" target=\"_blank\">#<span>vn69<\/span><\/a> <a href=\"https://masto.ai/tags/69vncom\" class=\"mention hashtag\" rel=\"nofollow noopener noreferrer\" target=\"_blank\">#<span>69vncom<\/span><\/a><br>SĐT        0397837429<\/p>"],"url":["https://masto.ai/@69vnwin"],"uri":["https://masto.ai/users/69vnwin"],"avatar":["https://files.mastodon.social/cache/accounts/avatars/111/176/747/005/400/061/original/2b55f6b13a79f943.png"],"avatar_static":["https://files.mastodon.social/cache/accounts/avatars/111/176/747/005/400/061/original/2b55f6b13a79f943.png"],"header":["https://files.mastodon.social/cache/accounts/headers/111/176/747/005/400/061/original/0a9f8e7eeca0f1fd.png"],"header_static":["https://files.mastodon.social/cache/accounts/headers/111/176/747/005/400/061/original/0a9f8e7eeca0f1fd.png"],"followers_count":[1],"following_count":[15],"statuses_count":[21],"last_status_at":["2023-12-29"],"hide_collections":[false],"emojis":[],"fields":[{"name":["Website"],"value":["<a href=\"https://69vn.win/\" rel=\"nofollow noopener noreferrer\" translate=\"no\" target=\"_blank\"><span class=\"invisible\">https://<\/span><span class=\"\">69vn.win/<\/span><span class=\"invisible\"><\/span><\/a>"],"verified_at":{}},{"name":["Linkedin"],"value":["<a href=\"https://www.linkedin.com/in/69vnwin/\" rel=\"nofollow noopener noreferrer\" translate=\"no\" target=\"_blank\"><span class=\"invisible\">https://www.<\/span><span class=\"\">linkedin.com/in/69vnwin/<\/span><span class=\"invisible\"><\/span><\/a>"],"verified_at":{}},{"name":["Pinterest"],"value":["<a href=\"https://www.pinterest.com/69vnwin/\" rel=\"nofollow noopener noreferrer\" translate=\"no\" target=\"_blank\"><span class=\"invisible\">https://www.<\/span><span class=\"\">pinterest.com/69vnwin/<\/span><span class=\"invisible\"><\/span><\/a>"],"verified_at":{}},{"name":["Twitter"],"value":["<a href=\"https://twitter.com/69vnwin\" rel=\"nofollow noopener noreferrer\" translate=\"no\" target=\"_blank\"><span class=\"invisible\">https://<\/span><span class=\"\">twitter.com/69vnwin<\/span><span class=\"invisible\"><\/span><\/a>"],"verified_at":{}}]}
