{"id":["1115350"],"username":["ronaldcollado"],"acct":["ronaldcollado"],"display_name":["Denver To Vail"],"locked":[false],"bot":[false],"discoverable":[false],"indexable":[false],"group":[false],"created_at":["2020-02-20T00:00:00.000Z"],"note":["<p>Denver To Vail discovers a private luxury Denver to Vail Shuttle, year round, with expert drivers in all weather conditions over the important location in the city. &lt;a href=&quot;<a href=\"https://www.denvertovail.com/denver-to-vail-transportation/\" target=\"_blank\" rel=\"nofollow noopener noreferrer\" translate=\"no\"><span class=\"invisible\">https://www.<\/span><span class=\"ellipsis\">denvertovail.com/denver-to-vai<\/span><span class=\"invisible\">l-transportation/<\/span><\/a>&quot;&gt;Denver To Vail Transportation&lt;/a&gt; also have high tech infotainment systems to keep yourself entertained, peace and comfort for a long journey ahead. Start Searching and Travel!<\/p>"],"url":["https://mastodon.social/@ronaldcollado"],"uri":["https://mastodon.social/users/ronaldcollado"],"avatar":["https://files.mastodon.social/accounts/avatars/001/115/350/original/e97e7685da01e5f2.jpg"],"avatar_static":["https://files.mastodon.social/accounts/avatars/001/115/350/original/e97e7685da01e5f2.jpg"],"header":["https://mastodon.social/headers/original/missing.png"],"header_static":["https://mastodon.social/headers/original/missing.png"],"followers_count":[1],"following_count":[1],"statuses_count":[0],"last_status_at":{},"hide_collections":{},"noindex":[false],"emojis":[],"roles":[],"fields":[]}
