{"id":["111619837524838378"],"username":["sangonomiya"],"acct":["sangonomiya"],"display_name":["Nas"],"locked":[false],"bot":[false],"discoverable":[true],"indexable":[true],"group":[false],"created_at":["2023-12-21T00:00:00.000Z"],"note":["<p>Asia | Filipino| @nascaw on Pinterest<\/p>"],"url":["https://mastodon.social/@sangonomiya"],"uri":["https://mastodon.social/users/sangonomiya"],"avatar":["https://files.mastodon.social/accounts/avatars/111/619/837/524/838/378/original/7b45c117a4b04f0f.jpeg"],"avatar_static":["https://files.mastodon.social/accounts/avatars/111/619/837/524/838/378/original/7b45c117a4b04f0f.jpeg"],"header":["https://files.mastodon.social/accounts/headers/111/619/837/524/838/378/original/5911cfdf78e69f8e.jpeg"],"header_static":["https://files.mastodon.social/accounts/headers/111/619/837/524/838/378/original/5911cfdf78e69f8e.jpeg"],"followers_count":[0],"following_count":[2],"statuses_count":[8],"last_status_at":["2024-08-11"],"hide_collections":{},"noindex":[false],"emojis":[],"roles":[],"fields":[]}
