{"id":["1167925"],"username":["Danielbachaco"],"acct":["Danielbachaco"],"display_name":["El Patriota Daniel"],"locked":[false],"bot":[false],"discoverable":[true],"indexable":[false],"group":[false],"created_at":["2020-04-04T00:00:00.000Z"],"note":["<p>Defensor del Auténtico Desarrollo Sostenible, incompatible con el capitalismo<\/p>"],"url":["https://mastodon.social/@Danielbachaco"],"uri":["https://mastodon.social/users/Danielbachaco"],"avatar":["https://files.mastodon.social/accounts/avatars/001/167/925/original/419fafa5f0f95e87.jpg"],"avatar_static":["https://files.mastodon.social/accounts/avatars/001/167/925/original/419fafa5f0f95e87.jpg"],"header":["https://files.mastodon.social/accounts/headers/001/167/925/original/716c78ddad1ac699.jpg"],"header_static":["https://files.mastodon.social/accounts/headers/001/167/925/original/716c78ddad1ac699.jpg"],"followers_count":[1],"following_count":[1],"statuses_count":[2],"last_status_at":["2020-04-04"],"hide_collections":{},"noindex":[false],"emojis":[],"roles":[],"fields":[]}
