{"id":["1169744"],"username":["Gabrielasjr"],"acct":["Gabrielasjr"],"display_name":["Gabriela S Jiménez Ramírez"],"locked":[false],"bot":[false],"discoverable":[false],"indexable":[false],"group":[false],"created_at":["2020-04-04T00:00:00.000Z"],"note":["<p>Bióloga - Nunca te des por vencido<\/p>"],"url":["https://mastodon.social/@Gabrielasjr"],"uri":["https://mastodon.social/users/Gabrielasjr"],"avatar":["https://files.mastodon.social/accounts/avatars/001/169/744/original/2034b9b25f31d9aa.jpg"],"avatar_static":["https://files.mastodon.social/accounts/avatars/001/169/744/original/2034b9b25f31d9aa.jpg"],"header":["https://files.mastodon.social/accounts/headers/001/169/744/original/33b478fb9f3e3a8c.jpg"],"header_static":["https://files.mastodon.social/accounts/headers/001/169/744/original/33b478fb9f3e3a8c.jpg"],"followers_count":[65],"following_count":[2],"statuses_count":[10],"last_status_at":["2020-05-21"],"hide_collections":{},"noindex":[false],"emojis":[],"roles":[],"fields":[]}
