{"id":["143000"],"username":["korenchkin"],"acct":["korenchkin@chaos.social"],"display_name":["Max"],"locked":[false],"bot":[false],"group":[false],"created_at":["2017-05-19"],"note":["<p>Math, Programming, Music, Mixology (not necessarily in that order) … and now also Theoretical Computer Science.<\/p>"],"url":["https://chaos.social/@korenchkin"],"avatar":["https://files.mastodon.social/cache/accounts/avatars/000/143/000/original/8ee58ee0bbc1528e.jpg"],"avatar_static":["https://files.mastodon.social/cache/accounts/avatars/000/143/000/original/8ee58ee0bbc1528e.jpg"],"header":["https://files.mastodon.social/cache/accounts/headers/000/143/000/original/2a19f6402a730d1b.jpg"],"header_static":["https://files.mastodon.social/cache/accounts/headers/000/143/000/original/2a19f6402a730d1b.jpg"],"followers_count":[390],"following_count":[774],"statuses_count":[4979],"fields":[{"name":"Pronouns","value":"hen/hens, they/them"},{"name":"Languages","value":"de-N, en-4, sv-2"},{"name":"Website","value":"<a href=\"https://kbs.inf.tu-dresden.de/max\" rel=\"nofollow noopener noreferrer\" translate=\"no\" target=\"_blank\"><span class=\"invisible\">https://<\/span><span class=\"\">kbs.inf.tu-dresden.de/max<\/span><span class=\"invisible\"><\/span><\/a>"},{"name":"Cuteness","value":"<span class=\"h-card\" translate=\"no\"><a href=\"https://plushies.social/@augustus\" class=\"u-url mention\" rel=\"nofollow noopener noreferrer\" target=\"_blank\">@<span>augustus@plushies.social<\/span><\/a><\/span>"}],"emojis":[],"discoverable":[true]}
