{"id":["26407"],"username":["Salayanara"],"acct":["Salayanara"],"display_name":["Kim 🍙"],"locked":[false],"bot":[false],"discoverable":[true],"indexable":[false],"group":[false],"created_at":["2017-03-30T00:00:00.000Z"],"note":["<p>J&#39;habite chez mon chat. J&#39;essaie de dessiner aussi.<\/p><p><a href=\"http://salayanara.deviantart.com\" target=\"_blank\" rel=\"nofollow noopener noreferrer\" translate=\"no\"><span class=\"invisible\">http://<\/span><span class=\"\">salayanara.deviantart.com<\/span><span class=\"invisible\"><\/span><\/a><\/p>"],"url":["https://mastodon.social/@Salayanara"],"uri":["https://mastodon.social/users/Salayanara"],"avatar":["https://files.mastodon.social/accounts/avatars/000/026/407/original/5a4377f5de6d0ecd.jpeg"],"avatar_static":["https://files.mastodon.social/accounts/avatars/000/026/407/original/5a4377f5de6d0ecd.jpeg"],"header":["https://files.mastodon.social/accounts/headers/000/026/407/original/f8503db28847646d.jpg"],"header_static":["https://files.mastodon.social/accounts/headers/000/026/407/original/f8503db28847646d.jpg"],"followers_count":[35],"following_count":[41],"statuses_count":[310],"last_status_at":["2023-05-14"],"hide_collections":[false],"noindex":[true],"emojis":[],"roles":[],"fields":[]}
