{"id":["490342"],"username":["mmci1525"],"acct":["mmci1525"],"display_name":["mmci1525"],"locked":[false],"bot":[false],"discoverable":{},"indexable":[false],"group":[false],"created_at":["2018-08-24T00:00:00.000Z"],"note":[""],"url":["https://mastodon.social/@mmci1525"],"uri":["https://mastodon.social/users/mmci1525"],"avatar":["https://files.mastodon.social/accounts/avatars/000/490/342/original/51f5b2eb655c9586.jpeg"],"avatar_static":["https://files.mastodon.social/accounts/avatars/000/490/342/original/51f5b2eb655c9586.jpeg"],"header":["https://files.mastodon.social/accounts/headers/000/490/342/original/48d223b2688b7a47.jpeg"],"header_static":["https://files.mastodon.social/accounts/headers/000/490/342/original/48d223b2688b7a47.jpeg"],"followers_count":[1],"following_count":[2],"statuses_count":[0],"last_status_at":{},"hide_collections":[false],"noindex":[false],"emojis":[],"roles":[],"fields":[]}
