{"id":["533838"],"username":["ruidoperro"],"acct":["ruidoperro"],"display_name":["Ruido Perro"],"locked":[false],"bot":[false],"discoverable":{},"indexable":[false],"group":[false],"created_at":["2018-09-20T00:00:00.000Z"],"note":["<p>De la piel hacia afuera está todo borroso.<\/p>"],"url":["https://mastodon.social/@ruidoperro"],"uri":["https://mastodon.social/users/ruidoperro"],"avatar":["https://files.mastodon.social/accounts/avatars/000/533/838/original/8d2804ffe073f36b.jpeg"],"avatar_static":["https://files.mastodon.social/accounts/avatars/000/533/838/original/8d2804ffe073f36b.jpeg"],"header":["https://files.mastodon.social/accounts/headers/000/533/838/original/e5dee064cb696d45.jpeg"],"header_static":["https://files.mastodon.social/accounts/headers/000/533/838/original/e5dee064cb696d45.jpeg"],"followers_count":[0],"following_count":[1],"statuses_count":[0],"last_status_at":{},"hide_collections":{},"noindex":[false],"emojis":[],"roles":[],"fields":[]}
