{"id":["604217"],"username":["Young_Atlas"],"acct":["Young_Atlas"],"display_name":["Constant Crisis"],"locked":[false],"bot":[false],"discoverable":{},"indexable":[false],"group":[false],"created_at":["2018-12-03T00:00:00.000Z"],"note":["<p>I’m trapped in a hole please send help<\/p>"],"url":["https://mastodon.social/@Young_Atlas"],"uri":["https://mastodon.social/users/Young_Atlas"],"avatar":["https://files.mastodon.social/accounts/avatars/000/604/217/original/2cccfff33b5869d8.jpeg"],"avatar_static":["https://files.mastodon.social/accounts/avatars/000/604/217/original/2cccfff33b5869d8.jpeg"],"header":["https://files.mastodon.social/accounts/headers/000/604/217/original/63039677e1eeeaa1.jpeg"],"header_static":["https://files.mastodon.social/accounts/headers/000/604/217/original/63039677e1eeeaa1.jpeg"],"followers_count":[0],"following_count":[1],"statuses_count":[5],"last_status_at":{},"hide_collections":{},"noindex":[false],"emojis":[],"roles":[],"fields":[{"name":["Tumblr?"],"value":["Wack"],"verified_at":{}},{"name":["Wig?"],"value":["Snatched"],"verified_at":{}},{"name":["Hotel?"],"value":["Trivago"],"verified_at":{}}]}
