{"id":["605814"],"username":["mintstring"],"acct":["mintstring"],"display_name":["mintstring"],"locked":[false],"bot":[false],"discoverable":{},"indexable":[false],"group":[false],"created_at":["2018-12-04T00:00:00.000Z"],"note":["<p>— hi! tea and comfy aesthetics are my bread and butter — <\/p><p>she/her<\/p>"],"url":["https://mastodon.social/@mintstring"],"uri":["https://mastodon.social/users/mintstring"],"avatar":["https://files.mastodon.social/accounts/avatars/000/605/814/original/b00df7c0c397fe71.jpeg"],"avatar_static":["https://files.mastodon.social/accounts/avatars/000/605/814/original/b00df7c0c397fe71.jpeg"],"header":["https://files.mastodon.social/accounts/headers/000/605/814/original/d2999596a535ba2f.jpeg"],"header_static":["https://files.mastodon.social/accounts/headers/000/605/814/original/d2999596a535ba2f.jpeg"],"followers_count":[17],"following_count":[51],"statuses_count":[7],"last_status_at":{},"hide_collections":[false],"noindex":[false],"emojis":[],"roles":[],"fields":[]}
