{"id":["875716"],"username":["srisrinu"],"acct":["srisrinu"],"display_name":["srisrinu"],"locked":[false],"bot":[false],"discoverable":[false],"indexable":[false],"group":[false],"created_at":["2019-08-06T00:00:00.000Z"],"note":["<p>I&#39;m interested in coding and automation kind of stuff<\/p>"],"url":["https://mastodon.social/@srisrinu"],"uri":["https://mastodon.social/users/srisrinu"],"avatar":["https://files.mastodon.social/accounts/avatars/000/875/716/original/5d7cab0ebeca7818.jpg"],"avatar_static":["https://files.mastodon.social/accounts/avatars/000/875/716/original/5d7cab0ebeca7818.jpg"],"header":["https://files.mastodon.social/accounts/headers/000/875/716/original/5a9f14ae403df132.jpg"],"header_static":["https://files.mastodon.social/accounts/headers/000/875/716/original/5a9f14ae403df132.jpg"],"followers_count":[1],"following_count":[2],"statuses_count":[0],"last_status_at":["2019-08-06"],"hide_collections":{},"noindex":[false],"emojis":[],"roles":[],"fields":[]}
