{"id":["968639"],"username":["Kaushalgautam"],"acct":["Kaushalgautam"],"display_name":["Kaushal"],"locked":[false],"bot":[false],"discoverable":[true],"indexable":[false],"group":[false],"created_at":["2019-11-08T00:00:00.000Z"],"note":["<p>Lawyer<\/p>"],"url":["https://mastodon.social/@Kaushalgautam"],"uri":["https://mastodon.social/users/Kaushalgautam"],"avatar":["https://files.mastodon.social/accounts/avatars/000/968/639/original/800d9ccab2be8b72.jpeg"],"avatar_static":["https://files.mastodon.social/accounts/avatars/000/968/639/original/800d9ccab2be8b72.jpeg"],"header":["https://files.mastodon.social/accounts/headers/000/968/639/original/3002457b4289bb0f.jpeg"],"header_static":["https://files.mastodon.social/accounts/headers/000/968/639/original/3002457b4289bb0f.jpeg"],"followers_count":[0],"following_count":[6],"statuses_count":[0],"last_status_at":{},"hide_collections":{},"noindex":[false],"emojis":[],"roles":[],"fields":[]}
